MANIFEST.in
README.rst
setup.py
kikyo_utils/__init__.py
kikyo_utils/analysis.py
kikyo_utils/constants.py
kikyo_utils/datetime.py
kikyo_utils/file.py
kikyo_utils/ip.py
kikyo_utils/logging.py
kikyo_utils/retry.py
kikyo_utils/selector.py
kikyo_utils.egg-info/PKG-INFO
kikyo_utils.egg-info/SOURCES.txt
kikyo_utils.egg-info/dependency_links.txt
kikyo_utils.egg-info/not-zip-safe
kikyo_utils.egg-info/requires.txt
kikyo_utils.egg-info/top_level.txt
requirements/test.txt
tests/__init__.py